testchapter/__init__.py
testchapter/address.py
testchapter/address_base.py
testchapter/functionaltest/__init__.py
testchapter/functionaltest/test_random_address.py
testchapter/unittest/__init__.py
testchapter/unittest/test_address.py
testchapter/unittest/test_address_base.py
testchapter-0.1.dist-info/LICENSE
testchapter-0.1.dist-info/METADATA
testchapter-0.1.dist-info/WHEEL
testchapter-0.1.dist-info/top_level.txt
testchapter-0.1.dist-info/RECORD
