Metadata-Version: 2.1
Name: testchapter
Version: 0.1
Summary: In kader van opdrachten voor de Stad Antwerpen en Digipolis
Home-page: https://github.com/janrum/testchapter
Author: Jan Rummens
Author-email: jan.rummens@digipolis.be
License: UNKNOWN
Platform: UNKNOWN
Classifier: Programming Language :: Python :: 3
Classifier: License :: OSI Approved :: Apache Software License
Classifier: Operating System :: OS Independent
